{
  "schemaVersion": "2026-07-21.yuukichiya-products.v1",
  "source": {
    "name": "勇吉屋商品一覧",
    "mode": "static-fallback",
    "updatedAt": "2026-07-21T00:00:00+09:00"
  },
  "items": [
    {
      "id": "junior-uniform",
      "status": "published",
      "sortOrder": 1,
      "title": "中学校制服",
      "lead": "市内最多数の商品を取り揃えております。kanko の制服は、他メーカ学生服に比べ3年間着用後のもちが違います。kanko の商品中でも最高級品の Feel Air ・ Fine Label をぜひお試しください。",
      "features": [
        "別注商品製作可能です。総ゴム仕様、ボタンなし仕様、マジックテープ仕様など、どんな仕様にもお応えします。",
        "KANKO Feel Air：制服日本1位メーカー＜カンコー＞のなかでも1番人気の学生服。",
        "KANKO STLEAD：欲しい機能全部で、コスパに優れたカンコーの学生服。",
        "オリジナルサイズUP：3年間安心のサイズupできる学生服。",
        "KANKO Fine Label：現役女子中高生とコラボして生まれた1番人気のセーラー服。",
        "KANKO Fine Label slim style：より細く、よりスッキリ、スタイル良く見えるスタイリッシュセーラー服。",
        "KANKO：カンコーのスタンダード、コスパに優れた数量限定セーラー服。",
        "着心地、スタイル、予算に応じてお選びください。"
      ],
      "targetStores": ["本店", "髙橋店"],
      "baseUrl": "",
      "images": [
        { "id": "uniform-01", "url": "assets/original/products/uniform-01.png", "alt": "KANKO Feel Air 学生服", "sortOrder": 1 },
        { "id": "uniform-02", "url": "assets/original/products/uniform-02.png", "alt": "KANKO STLEAD 学生服", "sortOrder": 2 },
        { "id": "uniform-03", "url": "assets/original/products/uniform-03.png", "alt": "KANKO セーラー服", "sortOrder": 3 },
        { "id": "uniform-04", "url": "assets/original/products/uniform-04.png", "alt": "KANKO Fine Label セーラー服", "sortOrder": 4 }
      ]
    },
    {
      "id": "junior-gym",
      "status": "published",
      "sortOrder": 2,
      "title": "中学校体操服",
      "lead": "勇吉屋特製ジャージ。販売店によってジャージ・体操服も違います。（一部の学校を除く）",
      "features": [
        "勇吉屋のジャージ・半袖・ハーフパンツ・体操着は、縫製・生地・型紙すべてオリジナルです。",
        "他店の物と比べ長期使用後のモチが違って、とっても丈夫です。近所の先輩方に聞いていただけると、非常にわかりやすいです。"
      ],
      "targetStores": ["本店", "髙橋店"],
      "baseUrl": "",
      "images": [
        { "id": "junior-gym-01", "url": "assets/original/products/junior-gym-01.jpg", "alt": "勇吉屋特製ジャージ", "sortOrder": 1 },
        { "id": "junior-gym-02", "url": "assets/original/products/junior-gym-02.jpg", "alt": "中学校体操服 半袖シャツ", "sortOrder": 2 },
        { "id": "junior-gym-03", "url": "assets/original/products/junior-gym-03.jpg", "alt": "中学校体操服 ハーフパンツ", "sortOrder": 3 }
      ]
    },
    {
      "id": "elementary-gym",
      "status": "published",
      "sortOrder": 3,
      "title": "小学校体操服",
      "lead": "半袖、長袖、ハーフパンツまで、学校生活に合わせて選べます。",
      "features": [
        "半袖吸汗速乾素材『どろよごれも落ちやすく、つきにくい』『抗菌防臭』『乾きが早く涼しい』『UVカット』。",
        "従来の袖と着丈に絞りのついたタイプと、Tシャツ（絞りの無い）タイプと2種類ございます。",
        "長袖速乾素材『汚れ落ちがいい』『乾きが早く温かい』『UVカット』。",
        "ハーフパンツは、他店の商品に比べ毛玉ができにくい、色落ちしにくい、生地がしっかりしていて長持ちします。"
      ],
      "targetStores": ["本店", "髙橋店"],
      "baseUrl": "",
      "images": [
        { "id": "elementary-gym-01", "url": "assets/original/products/elementary-gym-01.jpg", "alt": "小学校体操服", "sortOrder": 1 },
        { "id": "elementary-gym-02", "url": "assets/original/products/elementary-gym-02.jpg", "alt": "小学校体操服 長袖", "sortOrder": 2 },
        { "id": "elementary-gym-03", "url": "assets/original/products/elementary-gym-03.jpg", "alt": "小学校体操服 ハーフパンツ", "sortOrder": 3 }
      ]
    },
    {
      "id": "school-bag",
      "status": "published",
      "sortOrder": 4,
      "title": "通学バッグ",
      "lead": "勇吉屋で販売しております通学バッグは、学生専用に丈夫に作られたバッグです。",
      "features": [
        "スポーツバッグとは丈夫さが違います。自信をもってオススメします。",
        "写真は一例です。他にも市内最多数取り揃えております。カバン専門店にも負けない商品量です。"
      ],
      "targetStores": ["本店", "髙橋店"],
      "baseUrl": "",
      "images": [
        { "id": "school-bag-01", "url": "assets/original/products/school-bag-01.png", "alt": "通学バッグ", "sortOrder": 1 },
        { "id": "school-bag-02", "url": "assets/original/products/school-bag-02.jpg", "alt": "通学バッグ 商品例", "sortOrder": 2 },
        { "id": "school-bag-03", "url": "assets/original/products/school-bag-03.jpg", "alt": "通学バッグ 商品例", "sortOrder": 3 }
      ]
    },
    {
      "id": "loafer",
      "status": "published",
      "sortOrder": 5,
      "title": "EAST BOYローファー",
      "lead": "合皮ローファーで、お手入れが楽です。雨にも強く低反発クッション付き。",
      "features": ["人気急上昇の EASTBOY。低反発クッションでおススメです。"],
      "targetStores": ["本店", "髙橋店"],
      "baseUrl": "",
      "images": [
        { "id": "loafer-01", "url": "assets/original/products/loafer-01.jpg", "alt": "EAST BOYローファー", "sortOrder": 1 }
      ]
    },
    {
      "id": "school-shoes",
      "status": "published",
      "sortOrder": 6,
      "title": "通学くつ・うわばき 体育館シューズ",
      "lead": "写真は一例です。他にも多数取り揃えております。実際に履いてお確かめください。",
      "features": [
        "サイズ21cm～30cmまで幅広く取り揃えております。（商品によります）",
        "うわばき・体育館シューズは各学校によって異なります。詳しくは店頭でお尋ねください。学校指定品となります。"
      ],
      "targetStores": ["本店", "髙橋店"],
      "baseUrl": "",
      "images": [
        { "id": "commute-shoes-01", "url": "assets/original/products/commute-shoes-01.jpg", "alt": "通学くつ", "sortOrder": 1 },
        { "id": "commute-shoes-02", "url": "assets/original/products/commute-shoes-02.jpg", "alt": "通学くつ 商品例", "sortOrder": 2 },
        { "id": "commute-shoes-03", "url": "assets/original/products/commute-shoes-03.jpg", "alt": "通学くつ 商品例", "sortOrder": 3 },
        { "id": "commute-shoes-04", "url": "assets/original/products/commute-shoes-04.jpg", "alt": "通学くつ 商品例", "sortOrder": 4 },
        { "id": "indoor-shoes-01", "url": "assets/original/products/indoor-shoes-01.jpg", "alt": "うわばき・体育館シューズ", "sortOrder": 5 },
        { "id": "indoor-shoes-02", "url": "assets/original/products/indoor-shoes-02.png", "alt": "うわばき 商品例", "sortOrder": 6 },
        { "id": "indoor-shoes-03", "url": "assets/original/products/indoor-shoes-03.png", "alt": "体育館シューズ 商品例", "sortOrder": 7 },
        { "id": "indoor-shoes-04", "url": "assets/original/products/indoor-shoes-04.png", "alt": "体育館シューズ 商品例", "sortOrder": 8 }
      ]
    },
    {
      "id": "rainwear",
      "status": "published",
      "sortOrder": 7,
      "title": "雨合羽",
      "lead": "ストレッチ素材でよりスタイリッシュな学生用自転車通学雨合羽。",
      "features": [
        "軽くて動きやすいストレッチ素材を使用しています。",
        "透湿5,000g/㎡・24hで汗が蒸れにくく、耐水圧10,000mm以上です。",
        "前後面に反射パイピングを施しています。",
        "リュックを背負った状態で着用できるワイド背マチ仕様です。",
        "自転車ヘルメット対応で動くフード。ヘルメット未装着時も調整可能です。",
        "成長期に合わせて裾上げが可能です。"
      ],
      "targetStores": ["本店", "髙橋店"],
      "baseUrl": "",
      "images": [
        { "id": "rainwear-01", "url": "assets/original/products/rainwear-01.jpg", "alt": "雨合羽", "sortOrder": 1 }
      ]
    },
    {
      "id": "original-print",
      "status": "published",
      "sortOrder": 8,
      "title": "オリジナルプリントTシャツ 作ります。",
      "lead": "Tシャツ、トレーナー、ポロシャツ、パーカー、キャップ、ジャンバー、ビブス、ハッピ、エプロン、バンダナ、タオルなど、オリジナルプリントいたします。",
      "features": [
        "納期は2週間ほど。部活動、ダンスチーム、気の合う仲間と、お揃いのアイテムはいかがですか？",
        "ぜひご相談にご来店をお待ちしております。アイテムの載ったパンフレット差し上げます。"
      ],
      "targetStores": ["本店", "髙橋店"],
      "baseUrl": "",
      "images": [
        { "id": "print-shirt-01", "url": "assets/original/products/print-shirt-01.jpg", "alt": "オリジナルプリントTシャツ", "sortOrder": 1 }
      ]
    }
  ]
}
